<?xml version="1.0"?>
<opencv_storage>
<stage3>
  <maxWeakCount>19</maxWeakCount>
  <stageThreshold>-1.4997675418853760e+00</stageThreshold>
  <weakClassifiers>
    <_>
      <internalNodes>
        0 -1 1632 -269487117 -273682774 -67111945 -527445 -1 -808452145
        -134219777 -2049</internalNodes>
      <leafValues>
        -5.1822549104690552e-01 5.9756100177764893e-01</leafValues></_>
    <_>
      <internalNodes>
        0 -1 7776 -263254 -812916854 -305135744 -269487217 -1080560765
        84768002 1433916883 1432354815</internalNodes>
      <leafValues>
        -5.8577483892440796e-01 3.3955982327461243e-01</leafValues></_>
    <_>
      <internalNodes>
        0 -1 2332 -716049413 -148397365 -539099137 1339001579 -610075653
        -6315802 -8225 -536872257</internalNodes>
      <leafValues>
        -3.2452595233917236e-01 6.0404062271118164e-01</leafValues></_>
    <_>
      <internalNodes>
        0 -1 7307 -9046019 -543424528 1496808881 -51911 523401704
        -1087369996 454067707 -1124131603</internalNodes>
      <leafValues>
        -4.4742298126220703e-01 3.7988400459289551e-01</leafValues></_>
    <_>
      <internalNodes>
        0 -1 2430 -537461014 -97273090 1345470538 -549794817 -795685654
        1343234712 -545662051 1601568767</internalNodes>
      <leafValues>
        -4.9474501609802246e-01 3.5915285348892212e-01</leafValues></_>
    <_>
      <internalNodes>
        0 -1 6705 -1003620 -2932983 86060324 456669560 -80829543
        589891712 722643132 2143266813</internalNodes>
      <leafValues>
        -5.6130605936050415e-01 3.0583098530769348e-01</leafValues></_>
    <_>
      <internalNodes>
        0 -1 7501 -44979 -10800829 1660122863 -763470409 -42084340
        -14682593 -1201882369 -1291257221</internalNodes>
      <leafValues>
        -4.0924876928329468e-01 4.2242437601089478e-01</leafValues></_>
    <_>
      <internalNodes>
        0 -1 7256 -219483710 -609599617 1070687824 -543015217
        -1303207517 19232168 -472742495 -1019230293</internalNodes>
      <leafValues>
        -4.8189198970794678e-01 3.6507216095924377e-01</leafValues></_>
    <_>
      <internalNodes>
        0 -1 4724 1568570613 -8749323 -88933121 -128422035 -541144870
        -45661557 -1075905793 -1074632837</internalNodes>
      <leafValues>
        -4.2155200242996216e-01 4.1326373815536499e-01</leafValues></_>
    <_>
      <internalNodes>
        0 -1 7915 -228863921 1566537047 -471335314 1147599695 -499716030
        -704643225 -88867333 -766784673</internalNodes>
      <leafValues>
        -3.5381439328193665e-01 4.7285369038581848e-01</leafValues></_>
    <_>
      <internalNodes>
        0 -1 5363 -1202827052 -1080052777 -26179 -35768267 -1428955937
        -1054213 -2000532338 -1076166577</internalNodes>
      <leafValues>
        -4.6945428848266602e-01 3.2668411731719971e-01</leafValues></_>
    <_>
      <internalNodes>
        0 -1 3064 -9437465 550326254 -132128192 2128608975 846196301
        273931210 1934943813 -134479873</internalNodes>
      <leafValues>
        -4.2208847403526306e-01 3.7653723359107971e-01</leafValues></_>
    <_>
      <internalNodes>
        0 -1 6392 238305045 972345020 1005909951 1031748473 1043611629
        1069967197 1027341247 -1658292028</internalNodes>
      <leafValues>
        -5.1015323400497437e-01 3.1419670581817627e-01</leafValues></_>
    <_>
      <internalNodes>
        0 -1 6994 -27003444 -141562501 -213224926 -202673272 -1527382642
        1134160396 397226130 1464451583</internalNodes>
      <leafValues>
        -4.9803394079208374e-01 3.1349617242813110e-01</leafValues></_>
    <_>
      <internalNodes>
        0 -1 4663 428649996 528420656 -382474209 454899997 -833432068
        526324158 1236986475 89128895</internalNodes>
      <leafValues>
        -6.4738082885742188e-01 2.6349619030952454e-01</leafValues></_>
    <_>
      <internalNodes>
        0 -1 748 78549632 2140124033 -840469194 -175117733 154005983
        -608189518 172700879 -857761851</internalNodes>
      <leafValues>
        -4.8599028587341309e-01 3.1321579217910767e-01</leafValues></_>
    <_>
      <internalNodes>
        0 -1 8262 -271844401 -1884356694 -337120527 -471007288
        1743988351 -1937834025 1978455281 -235077634</internalNodes>
      <leafValues>
        -3.7060153484344482e-01 4.2146369814872742e-01</leafValues></_>
    <_>
      <internalNodes>
        0 -1 5199 1568146549 536179928 -34048129 -1206888707 -1664578066
        2142915130 -1111983233 -1616365634</internalNodes>
      <leafValues>
        -4.4627565145492554e-01 3.5170707106590271e-01</leafValues></_>
    <_>
      <internalNodes>
        0 -1 3596 -604519730 1525580512 82638 1939312882 1311015040
        46215974 1869243605 934639606</internalNodes>
      <leafValues>
        -6.3453549146652222e-01 2.7060416340827942e-01</leafValues></_></weakClassifiers></stage3>
</opencv_storage>
